<odoo>
    <data>
        <template id="assets_backend" name="custom page assets" inherit_id="web.assets_backend">
            <xpath expr="//script[last()]" position="after">
                <script type="text/javascript" src="/security/static/src/js/dashboard.js"/>
                <script type="text/javascript" src="/security/static/src/js/chart.min.js"/>
                <script type="text/javascript" src="/security/static/src/js/ui_datepicker_es.js"/>
                <link rel="stylesheet" href="/security/static/src/css/dashboard.css"/>
            </xpath>
        </template>
    </data>
</odoo>